web_tools/__init__.py
web_tools/aiohttp/__init__.py
web_tools/aiohttp/trace_config_log/__init__.py
web_tools/aiohttp/trace_config_log/context.py
web_tools/aiohttp/trace_config_log/model_mixin.py
web_tools/aiohttp/trace_config_log/trace_config.py
web_tools/fastapi/__init__.py
web_tools/fastapi/request_log/__init__.py
web_tools/fastapi/request_log/context.py
web_tools/fastapi/request_log/middleware.py
web_tools/fastapi/request_log/model_mixin.py
web_tools-0.6.5.dist-info/WHEEL
web_tools-0.6.5.dist-info/METADATA
web_tools-0.6.5.dist-info/RECORD
